setup.py
libgeb/__init__.py
libgeb/libgeb.py
libgeb/reader.py
libgeb.egg-info/PKG-INFO
libgeb.egg-info/SOURCES.txt
libgeb.egg-info/dependency_links.txt
libgeb.egg-info/top_level.txt