Metadata-Version: 1.1
Name: libgeb
Version: 0.1.0
Summary: A library for reading and writing binary genomic element files.
Home-page: https://github.com/antonybholmes/libgeb
Author: Antony B Holmes
Author-email: antony.b.holmes@gmail.com
License: UNKNOWN
Platform: UNKNOWN
Classifier: Programming Language :: Python :: 3
Classifier: License :: OSI Approved :: MIT License
Classifier: Operating System :: OS Independent
